[{"magnet": "magnet:?xt=urn:btih:af1e7f1c017e4274318b5bf9053d79572893c2e8", "magnet_date": "2017-11-10", "magnet_size": "18.53 GB", "magnet_name": "\u3010\u8096\u90a6\u9996\u53d1\u3011\u53d8\u5f62\u91d1\u521a5\uff1a\u6700\u540e\u7684\u9a91\u58eb\u56fd\u82f1\u53cc\u8bedTransformers.The.Last.Knight.2017.1080p.mkv"}, {"magnet": "magnet:?xt=urn:btih:cc87ce5b63ddf59f418f3cb36c46334e4679c500", "magnet_date": "2017-11-10", "magnet_size": "1.29 GB", "magnet_name": "\u53d8\u5f62\u91d1\u521a.2007.HD720P.\u82f1\u8bed\u4e2d\u5b57.mp4"}, {"magnet": "magnet:?xt=urn:btih:ae77221b7aa1038546cb2e11493138ccfa1041ea", "magnet_date": "2017-11-10", "magnet_size": "3.66 GB", "magnet_name": "[B\u4e4b\u5bb6www.btjia.cc]\u53d8\u5f62\u91d1\u521a5\uff1a\u6700\u540e\u7684\u9a91\u58eb\uff08\u5927\u9646\u516c\u6620\u53cc\u8bed\uff09.1080p.HD\u4e2d\u5b57[\u9ad8\u6e05\u7248\u8fc5\u96f7\u767e\u5ea6\u4e91BT\u7535\u5f71\u4e0b\u8f7d]"}, {"magnet": "magnet:?xt=urn:btih:4c9d76d26f8f5fd9bd7ae69aba83afbc38d01b18", "magnet_date": "2017-11-08", "magnet_size": "43.54 GB", "magnet_name": "\u53d8\u5f62\u91d1\u521a5\uff1a\u6700\u540e\u7684\u9a91\u58eb.Transformers.The.Last.Knight.2017.1080p.BluRay.AVC.Atmos.TrueHD7.1-HDHome"}, {"magnet": "magnet:?xt=urn:btih:78cc64556aba62c1e3da71c85710e63ec7e2eb5e", "magnet_date": "2017-11-06", "magnet_size": "2.49 GB", "magnet_name": "3DMAX\u53d8\u5f62\u91d1\u521a"}, {"magnet": "magnet:?xt=urn:btih:3f3a60922dd3f2f2712d117a2e78dae6ece2d967", "magnet_date": "2017-11-04", "magnet_size": "1.79 GB", "magnet_name": "\u3010\u9047\u89c1\u4ea4\u53cb\u7fa4\u3011\u53d8\u5f62\u91d1\u521a3"}, {"magnet": "magnet:?xt=urn:btih:589d1a6b5f875cf429e33371de3207b3cfebfd74", "magnet_date": "2017-11-02", "magnet_size": "2.9 GB", "magnet_name": "\u53d8\u5f62\u91d1\u521a5\uff1a\u6700\u540e\u7684\u9a91\u58eb.2017.HD720P.\u97e9\u7248\u4e2d\u82f1\u53cc\u5b57.[\u66f4\u591a\u8bf7\u5173\u6ce8\u516c\u4f17\u53f7\uff1a\u5c0f\u6cb3\u5f71\u89c6].mp4"}, {"magnet": "magnet:?xt=urn:btih:18cad1816d481e101704d03fa0999e4550852561", "magnet_date": "2017-11-01", "magnet_size": "5.33 GB", "magnet_name": "\u53d8\u5f62\u91d1\u521a1.Transformers.2007.BluRay.720p.x264.AC3.2Audios-CMCT.mkv"}, {"magnet": "magnet:?xt=urn:btih:9896f0a00194a60b18cd08fd0295c86feaccac57", "magnet_date": "2017-10-31", "magnet_size": "2.28 GB", "magnet_name": "\u53d8\u5f62\u91d1\u521a\uff1a\u6700\u540e\u7684\u9a91\u58eb.Transformers.The.Last.Knight.2017.1080p.Orange\u5b57\u5e55\u7ec4.mp4"}, {"magnet": "magnet:?xt=urn:btih:0b9d20d91139961a3432fedb073804d759a0f533", "magnet_date": "2017-10-30", "magnet_size": "7.32 GB", "magnet_name": "\u53d8\u5f62\u91d1\u521a5\uff1a\u6700\u540e\u7684\u9a91\u58eb2017\uff0c\u5173\u6ce8\u3010\u5b81\u6ce2\u66b4\u98ce\u52a8\u6f2b\u3011\u5fae\u4fe1\u516c\u4f17\u53f7\uff0c\u83b7\u53d6\u66f4\u591a\u8d44\u6e90"}, {"magnet": "magnet:?xt=urn:btih:9e96da711d9dce10621c8fddf057068c1c71130b", "magnet_date": "2017-10-27", "magnet_size": "5.94 GB", "magnet_name": "\u53d8\u5f62\u91d1\u521a5"}, {"magnet": "magnet:?xt=urn:btih:c7336ec78d493812874650e3c719af156cd707d2", "magnet_date": "2017-10-26", "magnet_size": "4.6 GB", "magnet_name": "\u53d8\u5f62\u91d1\u521a5\uff1a\u6700\u540e\u7684\u9a91\u58eb.Transformers.The.Last.Knight.2017.1080p.BluRay.x264-\u4e2d\u82f1\u53cc\u5b57-MP4BA.mp4"}, {"magnet": "magnet:?xt=urn:btih:0aa615d228c70c7dea71ebe7da2a2a658e0dbb48", "magnet_date": "2017-10-26", "magnet_size": "6.55 GB", "magnet_name": "\u3010\u8f68 \u8ff9\u3011\u53d8\u5f62\u91d1\u521a  \u2162"}, {"magnet": "magnet:?xt=urn:btih:2495a213252df0dbe8ec6496af126302ddbd8b17", "magnet_date": "2017-10-25", "magnet_size": "3.12 GB", "magnet_name": "\u53d8\u5f62\u91d1\u521a2\uff1a\u5377\u571f\u91cd\u6765\uffe1\u5723\u57celoveliness"}, {"magnet": "magnet:?xt=urn:btih:87c001f143a07df40a91d7afb36a7013ce36bd47", "magnet_date": "2017-10-25", "magnet_size": "2.28 GB", "magnet_name": "\u53d8\u5f62\u91d1\u521a\uff1a\u6700\u540e\u7684\u9a91\u58eb.Transformers.The.Last.Knight.2017.1080p.Orange\u5b57\u5e55\u7ec4.mp4"}, {"magnet": "magnet:?xt=urn:btih:0bad754cbf909141a088accae03478eabd486c01", "magnet_date": "2017-10-24", "magnet_size": "2.06 GB", "magnet_name": "[\u9633\u5149\u7535\u5f71www.ygdy8.com].\u53d8\u5f62\u91d1\u521a5\uff1a\u6700\u540e\u7684\u9a91\u58eb.BD.720p.\u4e2d\u82f1\u53cc\u5b57\u5e55.mkv"}, {"magnet": "magnet:?xt=urn:btih:cf22784c047a16a921e26908278b112d4d67439c", "magnet_date": "2017-10-24", "magnet_size": "345.5 MB", "magnet_name": "\u53d8\u5f62\u91d1\u521a\uff1a\u91cd\u62f3\u51fa\u51fb \u2014\u2014\u2014\u2014 \u7b80\u4f53\u4e2d\u6587\u786c\u76d8\u7248"}, {"magnet": "magnet:?xt=urn:btih:b81f4c75fc65a38199d4ccac83f891d7648ab29c", "magnet_date": "2017-10-24", "magnet_size": "17.14 GB", "magnet_name": "\u53d8\u5f62\u91d1\u521a\u3010\u5fae\u4fe1\u516c\u4f17\u53f7ZSBT666\u30111-4"}, {"magnet": "magnet:?xt=urn:btih:b8d10d2949b969907b00de5ce685f342c0205844", "magnet_date": "2017-10-24", "magnet_size": "3.42 GB", "magnet_name": "\u98de\u9e1f\u5a31\u4e50(bbs.hdbird.com).\u53d8\u5f62\u91d1\u521a4\uff1a\u7edd\u8ff9\u91cd\u751f.720p.\u4e2d\u82f1\u5b57\u5e55"}, {"magnet": "magnet:?xt=urn:btih:b1c984a4eacf9bf6458d1cf249942c1007d34452", "magnet_date": "2017-10-23", "magnet_size": "5.1 GB", "magnet_name": "\u53d8\u5f62\u91d1\u521a1.BD.mp4"}]